aiotelegraf/__init__.py
aiotelegraf/client.py
aiotelegraf/compat.py
aiotelegraf-0.4.0.dist-info/LICENSE
aiotelegraf-0.4.0.dist-info/WHEEL
aiotelegraf-0.4.0.dist-info/METADATA
aiotelegraf-0.4.0.dist-info/RECORD
