Metadata-Version: 2.1
Name: aiotelegraf
Version: 0.4.0
Summary: AsyncIO Python client for sending metrics to Telegraf
Home-page: https://github.com/Gr1N/aiotelegraf
License: MIT
Keywords: asyncio,telegraf,influx,tick
Author: Nikita Grishko
Author-email: gr1n@protonmail.com
Requires-Python: >=3.6,<4.0
Classifier: License :: OSI Approved :: MIT License
Classifier: Programming Language :: Python :: 3
Classifier: Programming Language :: Python :: 3.6
Classifier: Programming Language :: Python :: 3.7
Classifier: Programming Language :: Python :: 3.8
Classifier: Topic :: Software Development :: Libraries :: Python Modules
Requires-Dist: pytelegraf (>=0.3.3)
Project-URL: Repository, https://github.com/Gr1N/aiotelegraf
